{
    "package": {
        "resources": [
            {
                "pagetitle": "00 - Content - ContentBlocks",
                "longtitle": "Settings that influence how certain Bosons behave",
                "description": "",
                "introtext": "",
                "alias": "contentblocks",
                "menutitle": "ContentBlocks",
                "parent": "00 - Content",
                "file": "05_pages/hub/patterns/electrons/content/contentblocks.html",
                "properties": "05_pages/hub/patterns/electrons/content/contentblocks.json",
                "context_key": "hub",
                "content_type": "html",
                "template": "BasicDetailToC",
                "published": "1"
            },{
                "pagetitle": "00 - Content - CTAs",
                "longtitle": "Settings to manage and control Call To Actions",
                "description": "",
                "introtext": "",
                "alias": "cta",
                "menutitle": "CTAs",
                "parent": "00 - Content",
                "file": "05_pages/hub/patterns/electrons/content/cta.html",
                "properties": "05_pages/hub/patterns/electrons/content/cta.json",
                "context_key": "hub",
                "content_type": "html",
                "template": "BasicDetailToC",
                "published": "1"
            },{
                "pagetitle": "00 - Content - Footers",
                "longtitle": "These elements decide what happens in the footer",
                "description": "",
                "introtext": "",
                "alias": "footers",
                "menutitle": "Footers",
                "parent": "00 - Content",
                "file": "05_pages/hub/patterns/electrons/content/footers.html",
                "properties": "05_pages/hub/patterns/electrons/content/footers.json",
                "context_key": "hub",
                "content_type": "html",
                "template": "BasicDetailToC",
                "published": "1"
            },{
                "pagetitle": "00 - Content - Headers",
                "longtitle": "These elements decide what happens in the header",
                "description": "",
                "introtext": "",
                "alias": "headers",
                "menutitle": "Headers",
                "parent": "00 - Content",
                "file": "05_pages/hub/patterns/electrons/content/headers.html",
                "properties": "05_pages/hub/patterns/electrons/content/headers.json",
                "context_key": "hub",
                "content_type": "html",
                "template": "BasicDetailToC",
                "published": "1"
            },{
                "pagetitle": "00 - Content - Links",
                "longtitle": "Attach external sources to your pages",
                "description": "",
                "introtext": "",
                "alias": "links",
                "menutitle": "Links",
                "parent": "00 - Content",
                "file": "05_pages/hub/patterns/electrons/content/links.html",
                "properties": "05_pages/hub/patterns/electrons/content/links.json",
                "context_key": "hub",
                "content_type": "html",
                "template": "BasicDetailToC",
                "published": "1"
            },{
                "pagetitle": "00 - Content - Purpose",
                "longtitle": "Define what needs to be done and why it's needed",
                "description": "",
                "introtext": "",
                "alias": "purpose",
                "menutitle": "Purpose",
                "parent": "00 - Content",
                "file": "05_pages/hub/patterns/electrons/content/purpose.html",
                "properties": "05_pages/hub/patterns/electrons/content/purpose.json",
                "context_key": "hub",
                "content_type": "html",
                "template": "BasicDetailToC",
                "published": "1"
            },{
                "pagetitle": "00 - Content - Status",
                "longtitle": "Keep track of the condition of each page",
                "description": "",
                "introtext": "",
                "alias": "status",
                "menutitle": "Status",
                "parent": "00 - Content",
                "file": "05_pages/hub/patterns/electrons/content/status.html",
                "properties": "05_pages/hub/patterns/electrons/content/status.json",
                "context_key": "hub",
                "content_type": "html",
                "template": "BasicDetailToC",
                "published": "1"
            }
        ]
    }
}